polygon_tools/__init__.py
polygon_tools-1.0.1.dist-info/LICENSE
polygon_tools-1.0.1.dist-info/METADATA
polygon_tools-1.0.1.dist-info/WHEEL
polygon_tools-1.0.1.dist-info/top_level.txt
polygon_tools-1.0.1.dist-info/RECORD
