Metadata-Version: 2.1
Name: polygon-tools
Version: 1.0.1
Summary: Collection of polygon extensions.
Home-page: https://github.com/sgaebel/polygon_tools
Author: Dr. Sebastian M. Gaebel
Author-email: gaebel.sebastian@gmail.com
License: MIT
Keywords: geometry polygon
Classifier: Development Status :: 5 - Production/Stable
Classifier: Intended Audience :: Developers
Classifier: Topic :: Scientific/Engineering :: Mathematics
Classifier: License :: OSI Approved :: MIT License
Classifier: Programming Language :: Python :: 3.10
Classifier: Operating System :: POSIX :: Linux
Requires-Python: >=3.10
License-File: LICENSE
Requires-Dist: numpy
Requires-Dist: polygon-neighbours
Requires-Dist: polygons-share-edge
Requires-Dist: polygon-contains-point
